README.md
setup.cfg
setup.py
distributions/Binomialdistribution.py
distributions/Gaussiandistribution.py
distributions/Generaldistribution.py
distributions/__init__.py
distributionsbora.egg-info/PKG-INFO
distributionsbora.egg-info/SOURCES.txt
distributionsbora.egg-info/dependency_links.txt
distributionsbora.egg-info/not-zip-safe
distributionsbora.egg-info/top_level.txt